CODE_OF_CONDUCT.md
CONTRIBUTING.md
LICENSE
MANIFEST.in
README.md
requirements-dev.txt
requirements.txt
setup.py
TestSlide.egg-info/PKG-INFO
TestSlide.egg-info/SOURCES.txt
TestSlide.egg-info/dependency_links.txt
TestSlide.egg-info/entry_points.txt
TestSlide.egg-info/requires.txt
TestSlide.egg-info/top_level.txt
testslide/__init__.py
testslide/cli.py
testslide/dsl.py
testslide/import_profiler.py
testslide/lib.py
testslide/matchers.py
testslide/mock_callable.py
testslide/mock_constructor.py
testslide/patch.py
testslide/patch_attribute.py
testslide/py.typed
testslide/runner.py
testslide/strict_mock.py
testslide/version