Metadata-Version: 2.1
Name: TestSlide
Version: 2.7.0
Summary: A test framework for Python that makes mocking and iterating over code with tests a breeze
Home-page: https://github.com/facebook/TestSlide
Maintainer: Fabio Pugliese Ornellas
Maintainer-email: fabio.ornellas@gmail.com
License: MIT
Platform: UNKNOWN
Classifier: Development Status :: 5 - Production/Stable
Classifier: Intended Audience :: Developers
Classifier: License :: OSI Approved :: MIT License
Classifier: Operating System :: POSIX :: Linux
Classifier: Programming Language :: Python :: 3
Classifier: Topic :: Software Development :: Testing
Classifier: Topic :: Software Development :: Testing :: Acceptance
Classifier: Topic :: Software Development :: Testing :: BDD
Classifier: Topic :: Software Development :: Testing :: Mocking
Classifier: Topic :: Software Development :: Testing :: Unit  
Provides-Extra: build
